aiortsp/__init__.py
aiortsp/__version__.py
aiortsp/rtcp/__init__.py
aiortsp/rtcp/parser.py
aiortsp/rtcp/stats.py
aiortsp/rtsp/__init__.py
aiortsp/rtsp/auth.py
aiortsp/rtsp/connection.py
aiortsp/rtsp/errors.py
aiortsp/rtsp/parser.py
aiortsp/rtsp/reader.py
aiortsp/rtsp/sdp.py
aiortsp/rtsp/session.py
aiortsp/transport/__init__.py
aiortsp/transport/base.py
aiortsp/transport/tcp.py
aiortsp/transport/udp.py
aiortsp-1.4.0.dist-info/LICENSE
aiortsp-1.4.0.dist-info/METADATA
aiortsp-1.4.0.dist-info/WHEEL
aiortsp-1.4.0.dist-info/top_level.txt
aiortsp-1.4.0.dist-info/RECORD
