Metadata-Version: 2.1
Name: aiortsp
Version: 1.4.0
Summary: An asyncio-based RTSP library
Home-page: https://github.com/marss/aiortsp
Author: MARSS S.A.M.
Author-email: info@marss.com
License: GNU Lesser General Public License v3 or later
Keywords: asyncio,rtsp
Classifier: Development Status :: 4 - Beta
Classifier: Operating System :: OS Independent
Classifier: License :: OSI Approved :: GNU Lesser General Public License v3 (LGPLv3)
Classifier: Intended Audience :: Developers
Classifier: Programming Language :: Python :: 3
Classifier: Programming Language :: Python :: 3.6
Classifier: Programming Language :: Python :: 3.7
Classifier: Programming Language :: Python :: 3.8
Requires-Python: ~=3.6
License-File: LICENSE
Requires-Dist: dpkt~=1.9
